LICENSE.txt
MANIFEST.in
README.rst
VERSION.txt
requirements.txt
setup.cfg
setup.py
businesstemplates/__init__.py
businesstemplates/business_card_generator.py
businesstemplates/resume_generator.py
businesstemplates/utils.py
businesstemplates.egg-info/PKG-INFO
businesstemplates.egg-info/SOURCES.txt
businesstemplates.egg-info/dependency_links.txt
businesstemplates.egg-info/entry_points.txt
businesstemplates.egg-info/requires.txt
businesstemplates.egg-info/top_level.txt
businesstemplates/templates/Business Card Template.jpg
businesstemplates/templates/Email Icon Template.png
businesstemplates/templates/Phone Icon Template.png
businesstemplates/templates/Resume Template.docx