Metadata-Version: 2.1
Name: businesstemplates
Version: 1.0.0
Summary: An efficient command line tool to create resumes and business cards on the go!
Home-page: https://github.com/ThatGenZGamer48/Hackathon
Author: That GenZ Gamer
Author-email: thatgenzgamer@gmail.com
License: MIT
Project-URL: Bug Tracker, https://github.com/ThatGenZGamer48/Hackathon/issues
Project-URL: Source Code, https://github.com/ThatGenZGamer48/Hackathon
Keywords: Resume,Resume Generator,Business Card,Business Template,template,card
Platform: UNKNOWN
Classifier: Programming Language :: Python :: 3
Classifier: Programming Language :: Python :: 3.7
Classifier: Programming Language :: Python :: 3.8
Classifier: Programming Language :: Python :: 3.9
Classifier: Programming Language :: Python :: 3.10
Classifier: License :: OSI Approved :: MIT License
Classifier: Natural Language :: English
Classifier: Topic :: Internet
Classifier: Topic :: Utilities
Classifier: Typing :: Typed
Classifier: Operating System :: OS Independent
Requires-Python: >=3.7
License-File: LICENSE.txt
